MessageReceiverService/__init__.py
MessageReceiverService/__main__.py
MessageReceiverService/collection.py
MessageReceiverService/const.py
MessageReceiverService/service.py
pih_msg_rcv-1.21.dist-info/METADATA
pih_msg_rcv-1.21.dist-info/WHEEL
pih_msg_rcv-1.21.dist-info/entry_points.txt
pih_msg_rcv-1.21.dist-info/top_level.txt
pih_msg_rcv-1.21.dist-info/RECORD
