Metadata-Version: 2.1
Name: pih-msg-rcv
Version: 1.21
Summary: PIH Message receiver service package
Home-page: https://pacifichosp.com/
Author: Nikita Karachentsev
Author-email: it@pacifichosp.com
License: MIT
Requires-Dist: ipih
Requires-Dist: fastapi
Requires-Dist: uvicorn
